{
  "timestamp": "2026-06-30T13:27:30.501502+05:30",
  "marketOpen": true,
  "price": 23932.55,
  "open": 23798.3,
  "high": 24261.1,
  "low": 23790.25,
  "change": 134.25,
  "changePct": 0.56,
  "signal": "SELL",
  "crossover": null,
  "ema9": 23933.67,
  "ema15": 23934.75,
  "ema9Angle": -0.5,
  "emaStatus": "Negative",
  "vwap": 0,
  "vwapStatus": "Positive",
  "nearestSupport": null,
  "nearestResistance": null,
  "supportDist": null,
  "resistanceDist": null,
  "keyLevelStatus": "Negative",
  "levelDist": Infinity,
  "ssl": 23911.55,
  "bsl": 23964.35,
  "sslDist": 21.0,
  "bslDist": 31.8,
  "sslWarn": true,
  "bslWarn": true,
  "bankNifty": {
    "price": 57657.2,
    "change": 582.3,
    "changePct": 1.02,
    "ema9": 57681.76,
    "ema15": 57699.54,
    "status": "Negative"
  },
  "sensex": {
    "price": 76672.54,
    "change": 499.4,
    "changePct": 0.66,
    "ema9": 76698.53,
    "ema15": 76697.39,
    "status": "Positive"
  },
  "pattern": "Bullish Engulfing",
  "trendStatus": "Neutral"
}