{
  "timestamp": "2026-06-22T15:21:24.276323+05:30",
  "marketOpen": true,
  "price": 24093.45,
  "open": 23923.9,
  "high": 24188.95,
  "low": 23889.25,
  "change": 169.55,
  "changePct": 0.71,
  "signal": "SELL",
  "crossover": null,
  "ema9": 24110.96,
  "ema15": 24116.21,
  "ema9Angle": -1.1,
  "emaStatus": "Negative",
  "vwap": 0,
  "vwapStatus": "Positive",
  "nearestSupport": null,
  "nearestResistance": null,
  "supportDist": null,
  "resistanceDist": null,
  "keyLevelStatus": "Negative",
  "levelDist": Infinity,
  "ssl": 24091.85,
  "bsl": 24145.45,
  "sslDist": 1.6,
  "bslDist": 52.0,
  "sslWarn": true,
  "bslWarn": false,
  "bankNifty": {
    "price": 57915.25,
    "change": 603.5,
    "changePct": 1.05,
    "ema9": 57933.34,
    "ema15": 57927.0,
    "status": "Positive"
  },
  "sensex": {
    "price": 77135.89,
    "change": 609.12,
    "changePct": 0.8,
    "ema9": 77187.85,
    "ema15": 77190.49,
    "status": "Negative"
  },
  "pattern": "Inside Bar Breakout (Bull)",
  "trendStatus": "Neutral"
}